<AML>
 <Item type="RelationshipType" id="CEC8D0B0FC7A4FB5B6B2F7BE3FCD0D7D" action="add" dependencyLevel="0">
  <auto_search>1</auto_search>
  <behavior>float</behavior>
  <copy_permissions>0</copy_permissions>
  <create_related>0</create_related>
  <hide_in_all>0</hide_in_all>
  <inc_rel_key_name>1</inc_rel_key_name>
  <inc_related_key_name>1</inc_related_key_name>
  <is_list_type>0</is_list_type>
  <label xml:lang="en">Affected Items</label>
  <new_show_related>0</new_show_related>
  <related_id keyed_name="Change Controlled Item" type="ItemType" name="Change Controlled Item">198BF0BCCC364EE29F56434D803D5F1E</related_id>
  <related_notnull>0</related_notnull>
  <related_option>2</related_option>
  <relationship_id keyed_name="CM2 IR Chg Cntld Items" type="ItemType" name="CM2 IR Chg Cntld Items">
   <Item type="ItemType" id="69F3A81A97044D1ABDD57931EB207415" action="add">
    <allow_private_permission>1</allow_private_permission>
    <auto_search>0</auto_search>
    <enforce_discovery>0</enforce_discovery>
    <hide_where_used>0</hide_where_used>
    <implementation_type>table</implementation_type>
    <instance_data>CM2_IR_CHG_CNTLD_ITEMS</instance_data>
    <is_dependent>0</is_dependent>
    <is_relationship>1</is_relationship>
    <is_versionable>0</is_versionable>
    <revisions keyed_name="Default" type="Revision">7FE395DD8B9F4E1090756A34B733D75E</revisions>
    <show_parameters_tab>1</show_parameters_tab>
    <structure_view>tabs off</structure_view>
    <unlock_on_logout>0</unlock_on_logout>
    <use_src_access>1</use_src_access>
    <name>CM2 IR Chg Cntld Items</name>
    <Relationships />
   </Item>
  </relationship_id>
  <sort_order>128</sort_order>
  <source_id keyed_name="CM2 IR" type="ItemType" name="CM2 IR">622CD8AFA3174EDE8E074BC06B829AC2</source_id>
  <name>CM2 IR Chg Cntld Items</name>
 </Item>
 <Item type="View" action="delete" where="source_id='69F3A81A97044D1ABDD57931EB207415'" />
 <Item type="Form" action="delete" where="name='CM2 IR Chg Cntld Items'" />
</AML>