<AML>
 <Item type="Form" id="558BC306774448158C25F43BF505B59F" action="add">
  <category_form>0</category_form>
  <height>399</height>
  <stylesheet><![CDATA[../styles/default.css]]></stylesheet>
  <width>784</width>
  <name>CM2 Part Model</name>
  <Relationships>
   <Item type="Body" id="C1AA12DE4FAE4B24BC46663F40E2FBC3" action="add">
    <bg_color>#ffffff</bg_color>
    <sort_order>128</sort_order>
    <source_id keyed_name="CM2 Part Model" type="Form">558BC306774448158C25F43BF505B59F</source_id>
    <Relationships>
     <Item type="Field" id="D5D9959B78F9458E8F1D0B97D962D95F" action="add">
      <border_width>0</border_width>
      <display_length_unit>px</display_length_unit>
      <field_type>text</field_type>
      <font_color>#000000</font_color>
      <font_family>tahoma, arial, helvetica, sans-serif</font_family>
      <font_size>8pt</font_size>
      <font_weight>bold</font_weight>
      <is_disabled>0</is_disabled>
      <is_visible>1</is_visible>
      <label xml:lang="en">CAGE Code</label>
      <label_position>top</label_position>
      <list_no_blank>0</list_no_blank>
      <propertytype_id keyed_name="cage_code" type="Property">9022D2B4E7F847628EF0EAAF29CEDA2F</propertytype_id>
      <sort_order>5120</sort_order>
      <source_id keyed_name="C1AA12DE4FAE4B24BC46663F40E2FBC3" type="Body">C1AA12DE4FAE4B24BC46663F40E2FBC3</source_id>
      <tab_index>95384</tab_index>
      <tab_stop>1</tab_stop>
      <x>200</x>
      <y>250</y>
      <name>cage_code</name>
     </Item>
     <Item type="Field" id="41793AD558C44E82804A3992F2658224" action="add">
      <border_width>0</border_width>
      <css>{$this field rule} img  {  max-width: 150px;  max-height: 150px;  }</css>
      <display_length>114</display_length>
      <display_length_unit>px</display_length_unit>
      <field_type>class structure</field_type>
      <font_color>#000000</font_color>
      <font_family>arial, helvetica, sans-serif</font_family>
      <font_size>8pt</font_size>
      <font_weight>bold</font_weight>
      <is_disabled>0</is_disabled>
      <is_visible>1</is_visible>
      <label xml:lang="en">Type</label>
      <label_position>top</label_position>
      <list_no_blank>0</list_no_blank>
      <sort_order>256</sort_order>
      <source_id keyed_name="C1AA12DE4FAE4B24BC46663F40E2FBC3" type="Body">C1AA12DE4FAE4B24BC46663F40E2FBC3</source_id>
      <tab_stop>0</tab_stop>
      <x>200</x>
      <y>210</y>
      <name>classification</name>
      <Relationships>
       <Item type="Field Event" id="98B99196DD894ADDAC9F18B839EE4899" action="add">
        <field_event>onchange</field_event>
        <related_id keyed_name="Show Class-Specific Fields" type="Method">
         <Item type="Method" action="get" select="id">
          <name>Show Class-Specific Fields</name>
         </Item>
        </related_id>
        <sort_order>128</sort_order>
        <source_id keyed_name="classification" type="Field">41793AD558C44E82804A3992F2658224</source_id>
       </Item>
      </Relationships>
     </Item>
     <Item type="Field" id="368D7415EBFD40BA94AC4F1687D6AD10" action="add">
      <border_width>0</border_width>
      <display_length_unit>px</display_length_unit>
      <field_type>html</field_type>
      <font_color>#000000</font_color>
      <font_family>arial, helvetica, sans-serif</font_family>
      <font_size>8pt</font_size>
      <font_weight>bold</font_weight>
      <html_code><![CDATA[<table width="100%" style="border-collapse:collapse;" cellspacing="0px" cellpadding="0px">
<col style="background-color:#7C93E8; width:5px;vertical-align: top;">
<col style="vertical-align: top;">
<tbody>
<tr>
<td></td>
<td style="padding-left:15px; color:#7C93E8; font-weight:bold; text-align:left;" id="classNameTd">Properties</td>
</tr>
<tr>
<td height="50px"></td>
<td id="classSpecificFieldContainer" style="padding-left: 15px"></td>
</tr>
</tbody>
</table>]]></html_code>
      <is_disabled>0</is_disabled>
      <is_visible>0</is_visible>
      <list_no_blank>0</list_no_blank>
      <sort_order>384</sort_order>
      <source_id keyed_name="C1AA12DE4FAE4B24BC46663F40E2FBC3" type="Body">C1AA12DE4FAE4B24BC46663F40E2FBC3</source_id>
      <tab_stop>1</tab_stop>
      <x>200</x>
      <y>290</y>
      <name>classSpecificFields_border</name>
     </Item>
     <Item type="Field" id="82CD4AD7C0DC416AA8EA58C89FCBD3B8" action="add">
      <border_width>0</border_width>
      <display_length_unit>px</display_length_unit>
      <field_type>item</field_type>
      <font_color>#000000</font_color>
      <font_family>tahoma, arial, helvetica, sans-serif</font_family>
      <font_size>8pt</font_size>
      <font_weight>bold</font_weight>
      <is_disabled>1</is_disabled>
      <is_visible>1</is_visible>
      <label xml:lang="en">CN</label>
      <label_position>top</label_position>
      <list_no_blank>0</list_no_blank>
      <propertytype_id keyed_name="cn" type="Property">9D67000D1FCE4D10A6D44509418820D9</propertytype_id>
      <sort_order>4864</sort_order>
      <source_id keyed_name="C1AA12DE4FAE4B24BC46663F40E2FBC3" type="Body">C1AA12DE4FAE4B24BC46663F40E2FBC3</source_id>
      <tab_index>95128</tab_index>
      <tab_stop>1</tab_stop>
      <x>400</x>
      <y>210</y>
      <name>cn</name>
     </Item>
     <Item type="Field" id="C2F82236C18B48979EB6D68584B9CD02" action="add">
      <border_width>0</border_width>
      <display_length_unit>px</display_length_unit>
      <field_type>textarea</field_type>
      <font_color>#000000</font_color>
      <font_family>arial, helvetica, sans-serif</font_family>
      <font_size>8pt</font_size>
      <font_weight>bold</font_weight>
      <is_disabled>0</is_disabled>
      <is_visible>1</is_visible>
      <label xml:lang="en">Long Description</label>
      <label_position>top</label_position>
      <list_no_blank>0</list_no_blank>
      <propertytype_id keyed_name="description" type="Property">04EB70FA8BF04F2FBA12095F56F011A2</propertytype_id>
      <sort_order>768</sort_order>
      <source_id keyed_name="C1AA12DE4FAE4B24BC46663F40E2FBC3" type="Body">C1AA12DE4FAE4B24BC46663F40E2FBC3</source_id>
      <tab_index>60</tab_index>
      <tab_stop>1</tab_stop>
      <textarea_cols>328</textarea_cols>
      <textarea_rows>54</textarea_rows>
      <x>200</x>
      <y>130</y>
      <name>description</name>
     </Item>
     <Item type="Field" id="384DE2802BAC4EE69DFC719053630FFB" action="add">
      <border_width>0</border_width>
      <display_length>114</display_length>
      <display_length_unit>px</display_length_unit>
      <field_type>date</field_type>
      <font_color>#000000</font_color>
      <font_family>arial, helvetica, sans-serif</font_family>
      <font_size>8pt</font_size>
      <font_weight>bold</font_weight>
      <is_disabled>0</is_disabled>
      <is_visible>1</is_visible>
      <label xml:lang="en">Effective Date</label>
      <label_position>top</label_position>
      <list_no_blank>0</list_no_blank>
      <sort_order>896</sort_order>
      <source_id keyed_name="C1AA12DE4FAE4B24BC46663F40E2FBC3" type="Body">C1AA12DE4FAE4B24BC46663F40E2FBC3</source_id>
      <tab_stop>0</tab_stop>
      <x>570</x>
      <y>170</y>
      <name>effective_date</name>
     </Item>
     <Item type="Field" id="34A9CA53C7494BCCA6BC0B59D4C65236" action="add">
      <border_width>0</border_width>
      <display_length_unit>px</display_length_unit>
      <field_type>html</field_type>
      <font_color>#000000</font_color>
      <font_family>arial, helvetica, sans-serif</font_family>
      <font_size>8pt</font_size>
      <font_weight>bold</font_weight>
      <html_code><![CDATA[<input type="button" name="major_rev_increment" value="+" style="width: 16px" onclick="createNewRevision();" />
<script type="text/javascript">
function createNewRevision()
{
  if(!top.aras.confirm(top.aras.getResource("plm", "createnewrevision.confirm")))
  { 
    return;
  }
  var dom = top.aras.createXMLDocument();
  dom.loadXML(parent.item.xml);
  dom.documentElement.setAttribute('action', 'PE_CreateNewRevision');
	
  var res = top.aras.soapSend("ApplyMethod", dom.xml);
  if (res.getFaultCode() != 0)
  {
    top.aras.AlertError(res);
    return;
  }
  res = res.getResultsBody();
  dom.loadXML(res);

  top.aras.uiReShowItemEx(parent.itemID, dom.documentElement, parent.viewMode);
}
</script>]]></html_code>
      <is_disabled>0</is_disabled>
      <is_visible>1</is_visible>
      <label_position>top</label_position>
      <list_no_blank>0</list_no_blank>
      <sort_order>4608</sort_order>
      <source_id keyed_name="C1AA12DE4FAE4B24BC46663F40E2FBC3" type="Body">C1AA12DE4FAE4B24BC46663F40E2FBC3</source_id>
      <tab_stop>1</tab_stop>
      <x>360</x>
      <y>6</y>
      <name>generation_major_rev</name>
     </Item>
     <Item type="Field" id="C06053182A01470CA7A61814290DA689" action="add">
      <border_width>0</border_width>
      <display_length>114</display_length>
      <display_length_unit>px</display_length_unit>
      <field_type>checkbox</field_type>
      <font_color>#000000</font_color>
      <font_family>arial, helvetica, sans-serif</font_family>
      <font_size>8pt</font_size>
      <font_weight>bold</font_weight>
      <is_disabled>1</is_disabled>
      <is_visible>1</is_visible>
      <label xml:lang="en">Changes Pending</label>
      <label_position>right</label_position>
      <list_no_blank>0</list_no_blank>
      <propertytype_id keyed_name="has_change_pending" type="Property">668EB2233D4341329EE97449B0267E3A</propertytype_id>
      <sort_order>4352</sort_order>
      <source_id keyed_name="C1AA12DE4FAE4B24BC46663F40E2FBC3" type="Body">C1AA12DE4FAE4B24BC46663F40E2FBC3</source_id>
      <tab_index>900</tab_index>
      <tab_stop>0</tab_stop>
      <x>15</x>
      <y>290</y>
      <name>has_change_pending</name>
     </Item>
     <Item type="Field" id="769F45A8060B4FCAB1D232969348A1D4" action="add">
      <border_width>0</border_width>
      <display_length_unit>px</display_length_unit>
      <field_type>html</field_type>
      <font_color>#000000</font_color>
      <font_family>arial, helvetica, sans-serif</font_family>
      <font_size>8pt</font_size>
      <font_weight>bold</font_weight>
      <html_code><![CDATA[<span id="ITEM_INFO_INTERNAL_SPAN"/>
<script>
  populate_ITEM_INFO_INTERNAL_SPAN = function()
  {
    document.getElementById("ITEM_INFO_INTERNAL_SPAN").innerHTML = top.aras.uiDrawItemInfoTable(document.itemType);
    top.aras.uiPopulateInfoTableWithItem(document.item, document);
  }

window.addEventListener("load", populate_ITEM_INFO_INTERNAL_SPAN);

</script>]]></html_code>
      <is_disabled>0</is_disabled>
      <is_visible>1</is_visible>
      <label_position>top</label_position>
      <list_no_blank>0</list_no_blank>
      <sort_order>1024</sort_order>
      <source_id keyed_name="C1AA12DE4FAE4B24BC46663F40E2FBC3" type="Body">C1AA12DE4FAE4B24BC46663F40E2FBC3</source_id>
      <tab_stop>1</tab_stop>
      <x>1</x>
      <y>1</y>
      <name>item_info</name>
     </Item>
     <Item type="Field" id="5DFE56A07F1148F7BA663B94FDD734DB" action="add">
      <border_width>0</border_width>
      <display_length>114</display_length>
      <display_length_unit>px</display_length_unit>
      <field_type>text</field_type>
      <font_color>#000000</font_color>
      <font_family>arial, helvetica, sans-serif</font_family>
      <font_size>8pt</font_size>
      <font_weight>bold</font_weight>
      <is_disabled>0</is_disabled>
      <is_visible>1</is_visible>
      <label xml:lang="en">Part Number</label>
      <label_position>top</label_position>
      <list_no_blank>0</list_no_blank>
      <propertytype_id keyed_name="item_number" type="Property">879EAA0579BD4120BF3DF324ABA7A341</propertytype_id>
      <sort_order>1920</sort_order>
      <source_id keyed_name="C1AA12DE4FAE4B24BC46663F40E2FBC3" type="Body">C1AA12DE4FAE4B24BC46663F40E2FBC3</source_id>
      <tab_index>5</tab_index>
      <tab_stop>1</tab_stop>
      <x>200</x>
      <y>10</y>
      <name>item_number</name>
     </Item>
     <Item type="Field" id="34CE3DF8B220417A84092464856DE3F7" action="add">
      <border_width>0</border_width>
      <display_length_unit>px</display_length_unit>
      <field_type>text</field_type>
      <font_color>#000000</font_color>
      <font_family>tahoma, arial, helvetica, sans-serif</font_family>
      <font_size>8pt</font_size>
      <font_weight>bold</font_weight>
      <is_disabled>0</is_disabled>
      <is_visible>1</is_visible>
      <label xml:lang="en">Lot</label>
      <label_position>top</label_position>
      <list_no_blank>0</list_no_blank>
      <propertytype_id keyed_name="lot" type="Property">718239483D9A404395F512CDF805859E</propertytype_id>
      <sort_order>5504</sort_order>
      <source_id keyed_name="C1AA12DE4FAE4B24BC46663F40E2FBC3" type="Body">C1AA12DE4FAE4B24BC46663F40E2FBC3</source_id>
      <tab_index>95768</tab_index>
      <tab_stop>1</tab_stop>
      <x>400</x>
      <y>250</y>
      <name>lot</name>
     </Item>
     <Item type="Field" id="DBD330939C8448369C27236E69F4816C" action="add">
      <border_width>0</border_width>
      <css>{$this field rule} input
{
  width: 20px;
}
</css>
      <display_length>48</display_length>
      <display_length_unit>px</display_length_unit>
      <field_type>text</field_type>
      <font_color>#000000</font_color>
      <font_family>arial, helvetica, sans-serif</font_family>
      <font_size>8pt</font_size>
      <font_weight>bold</font_weight>
      <html_code><![CDATA[<input type="text" name="major_rev" disabled value="REV" populate="1"/>]]></html_code>
      <is_disabled>1</is_disabled>
      <is_visible>1</is_visible>
      <label xml:lang="en">Revision</label>
      <label_position>top</label_position>
      <list_no_blank>0</list_no_blank>
      <sort_order>1152</sort_order>
      <source_id keyed_name="C1AA12DE4FAE4B24BC46663F40E2FBC3" type="Body">C1AA12DE4FAE4B24BC46663F40E2FBC3</source_id>
      <tab_stop>0</tab_stop>
      <x>330</x>
      <y>10</y>
      <name>major_rev</name>
     </Item>
     <Item type="Field" id="677A9A701F8A47F8BD0B1FDD219F3999" action="add">
      <border_width>0</border_width>
      <display_length_unit>px</display_length_unit>
      <field_type>dropdown</field_type>
      <font_color>#000000</font_color>
      <font_family>arial, helvetica, sans-serif</font_family>
      <font_size>8pt</font_size>
      <font_weight>bold</font_weight>
      <is_disabled>0</is_disabled>
      <is_visible>1</is_visible>
      <label xml:lang="en">Make / Buy</label>
      <label_position>top</label_position>
      <list_no_blank>0</list_no_blank>
      <propertytype_id keyed_name="make_buy" type="Property">F95E298391874E21A825EF5B0238B1C7</propertytype_id>
      <sort_order>1280</sort_order>
      <source_id keyed_name="C1AA12DE4FAE4B24BC46663F40E2FBC3" type="Body">C1AA12DE4FAE4B24BC46663F40E2FBC3</source_id>
      <tab_index>50</tab_index>
      <tab_stop>1</tab_stop>
      <x>290</x>
      <y>90</y>
      <name>make_buy</name>
     </Item>
     <Item type="Field" id="DAEDA95CED694F7BBC1A4AE0F63D5899" action="add">
      <border_width>0</border_width>
      <display_length>114</display_length>
      <display_length_unit>px</display_length_unit>
      <field_type>item</field_type>
      <font_color>#000000</font_color>
      <font_family>arial, helvetica, sans-serif</font_family>
      <font_size>8pt</font_size>
      <font_weight>bold</font_weight>
      <is_disabled>0</is_disabled>
      <is_visible>1</is_visible>
      <label xml:lang="en">Designated User</label>
      <label_position>top</label_position>
      <list_no_blank>0</list_no_blank>
      <sort_order>1408</sort_order>
      <source_id keyed_name="C1AA12DE4FAE4B24BC46663F40E2FBC3" type="Body">C1AA12DE4FAE4B24BC46663F40E2FBC3</source_id>
      <tab_index>30</tab_index>
      <tab_stop>1</tab_stop>
      <x>570</x>
      <y>50</y>
      <name>managed_by_id</name>
     </Item>
     <Item type="Field" id="14663B64D4C24CCC8EFBF780AA8CFDBA" action="add">
      <border_width>0</border_width>
      <display_length_unit>px</display_length_unit>
      <field_type>item</field_type>
      <font_color>#000000</font_color>
      <font_family>tahoma, arial, helvetica, sans-serif</font_family>
      <font_size>8pt</font_size>
      <font_weight>bold</font_weight>
      <is_disabled>0</is_disabled>
      <is_visible>1</is_visible>
      <label xml:lang="en">Model</label>
      <label_position>top</label_position>
      <list_no_blank>0</list_no_blank>
      <propertytype_id keyed_name="model_id" type="Property">BC6BA1A8171F4C559EF19FE70F7B847D</propertytype_id>
      <sort_order>5248</sort_order>
      <source_id keyed_name="C1AA12DE4FAE4B24BC46663F40E2FBC3" type="Body">C1AA12DE4FAE4B24BC46663F40E2FBC3</source_id>
      <tab_index>95512</tab_index>
      <tab_stop>1</tab_stop>
      <x>200</x>
      <y>290</y>
      <name>model_id</name>
     </Item>
     <Item type="Field" id="4521F2E30F35457790FBD603C416952A" action="add">
      <border_width>0</border_width>
      <display_length>323</display_length>
      <display_length_unit>px</display_length_unit>
      <field_type>text</field_type>
      <font_color>#000000</font_color>
      <font_family>arial, helvetica, sans-serif</font_family>
      <font_size>8pt</font_size>
      <font_weight>bold</font_weight>
      <is_disabled>0</is_disabled>
      <is_visible>1</is_visible>
      <label xml:lang="en">Name</label>
      <label_position>top</label_position>
      <list_no_blank>0</list_no_blank>
      <propertytype_id keyed_name="name" type="Property">6DE61A89F16848049DF8967B51FD7F58</propertytype_id>
      <sort_order>1664</sort_order>
      <source_id keyed_name="C1AA12DE4FAE4B24BC46663F40E2FBC3" type="Body">C1AA12DE4FAE4B24BC46663F40E2FBC3</source_id>
      <tab_index>20</tab_index>
      <tab_stop>1</tab_stop>
      <x>200</x>
      <y>50</y>
      <name>name</name>
     </Item>
     <Item type="Field" id="AAB0A203C4E242EB9F5153695216FCA5" action="add">
      <border_width>0</border_width>
      <display_length>114</display_length>
      <display_length_unit>px</display_length_unit>
      <field_type>item</field_type>
      <font_color>#000000</font_color>
      <font_family>arial, helvetica, sans-serif</font_family>
      <font_size>8pt</font_size>
      <font_weight>bold</font_weight>
      <is_disabled>0</is_disabled>
      <is_visible>1</is_visible>
      <label xml:lang="en">Assigned Creator</label>
      <label_position>top</label_position>
      <list_no_blank>0</list_no_blank>
      <sort_order>1792</sort_order>
      <source_id keyed_name="C1AA12DE4FAE4B24BC46663F40E2FBC3" type="Body">C1AA12DE4FAE4B24BC46663F40E2FBC3</source_id>
      <tab_index>10</tab_index>
      <tab_stop>1</tab_stop>
      <x>570</x>
      <y>10</y>
      <name>owned_by_id</name>
     </Item>
     <Item type="Field" id="650F419C4A194AACAD390AFCC546DDDC" action="add">
      <border_width>0</border_width>
      <display_length_unit>px</display_length_unit>
      <field_type>date</field_type>
      <font_color>#000000</font_color>
      <font_family>tahoma, arial, helvetica, sans-serif</font_family>
      <font_size>8pt</font_size>
      <font_weight>bold</font_weight>
      <is_disabled>0</is_disabled>
      <is_visible>1</is_visible>
      <label xml:lang="en">Release Date</label>
      <label_position>top</label_position>
      <list_no_blank>0</list_no_blank>
      <sort_order>5632</sort_order>
      <source_id keyed_name="C1AA12DE4FAE4B24BC46663F40E2FBC3" type="Body">C1AA12DE4FAE4B24BC46663F40E2FBC3</source_id>
      <tab_index>2944</tab_index>
      <tab_stop>1</tab_stop>
      <x>570</x>
      <y>130</y>
      <name>release_date</name>
     </Item>
     <Item type="Field" id="CDD8EB74F36942B3BAE644DBA24B4936" action="add">
      <border_width>0</border_width>
      <display_length_unit>px</display_length_unit>
      <field_type>date</field_type>
      <font_color>#000000</font_color>
      <font_family>tahoma, arial, helvetica, sans-serif</font_family>
      <font_size>8pt</font_size>
      <font_weight>bold</font_weight>
      <is_disabled>0</is_disabled>
      <is_visible>1</is_visible>
      <label xml:lang="en">Plan Release Date</label>
      <label_position>top</label_position>
      <list_no_blank>0</list_no_blank>
      <propertytype_id keyed_name="release_date_plan" type="Property">4DFD2ED285794D5198ECA25CEAE7BE25</propertytype_id>
      <sort_order>4992</sort_order>
      <source_id keyed_name="C1AA12DE4FAE4B24BC46663F40E2FBC3" type="Body">C1AA12DE4FAE4B24BC46663F40E2FBC3</source_id>
      <tab_index>95256</tab_index>
      <tab_stop>1</tab_stop>
      <x>570</x>
      <y>90</y>
      <name>release_date_plan</name>
     </Item>
     <Item type="Field" id="8A21CF7D6B304AA7B4A208D0E73C6E5E" action="add">
      <border_width>0</border_width>
      <display_length_unit>px</display_length_unit>
      <field_type>text</field_type>
      <font_color>#000000</font_color>
      <font_family>tahoma, arial, helvetica, sans-serif</font_family>
      <font_size>8pt</font_size>
      <font_weight>bold</font_weight>
      <is_disabled>0</is_disabled>
      <is_visible>1</is_visible>
      <label xml:lang="en">Serial Number</label>
      <label_position>top</label_position>
      <list_no_blank>0</list_no_blank>
      <propertytype_id keyed_name="serial_number" type="Property">11E6CBE893D4402EA80E47371EAF0A73</propertytype_id>
      <sort_order>5376</sort_order>
      <source_id keyed_name="C1AA12DE4FAE4B24BC46663F40E2FBC3" type="Body">C1AA12DE4FAE4B24BC46663F40E2FBC3</source_id>
      <tab_index>95640</tab_index>
      <tab_stop>1</tab_stop>
      <x>400</x>
      <y>290</y>
      <name>serial_number</name>
     </Item>
     <Item type="Field" id="65C8ACA2C6EB4B47AEE156CD0CB35721" action="add">
      <border_width>0</border_width>
      <css />
      <display_length>91</display_length>
      <display_length_unit>px</display_length_unit>
      <field_type>text</field_type>
      <font_color>#000000</font_color>
      <font_family>arial, helvetica, sans-serif</font_family>
      <font_size>8pt</font_size>
      <font_weight>bold</font_weight>
      <height>38</height>
      <is_disabled>1</is_disabled>
      <is_visible>1</is_visible>
      <label xml:lang="en">State</label>
      <label_position>top</label_position>
      <list_no_blank>0</list_no_blank>
      <sort_order>2176</sort_order>
      <source_id keyed_name="C1AA12DE4FAE4B24BC46663F40E2FBC3" type="Body">C1AA12DE4FAE4B24BC46663F40E2FBC3</source_id>
      <tab_stop>0</tab_stop>
      <width>160</width>
      <x>390</x>
      <y>10</y>
      <name>state</name>
     </Item>
     <Item type="Field" id="9E8BE0A1E9EB46C59C091F644A1912F6" action="add">
      <border_width>0</border_width>
      <display_length_unit>px</display_length_unit>
      <field_type>image</field_type>
      <font_color>#000000</font_color>
      <font_family>arial, helvetica, sans-serif</font_family>
      <font_size>8pt</font_size>
      <font_weight>bold</font_weight>
      <height>150</height>
      <is_disabled>0</is_disabled>
      <is_visible>1</is_visible>
      <label_position>top</label_position>
      <list_no_blank>0</list_no_blank>
      <propertytype_id keyed_name="thumbnail" type="Property">29CCA13C125B47A3B4723101F5443B00</propertytype_id>
      <sort_order>4480</sort_order>
      <source_id keyed_name="C1AA12DE4FAE4B24BC46663F40E2FBC3" type="Body">C1AA12DE4FAE4B24BC46663F40E2FBC3</source_id>
      <tab_stop>1</tab_stop>
      <width>150</width>
      <x>570</x>
      <y>220</y>
      <name>thumbnail</name>
     </Item>
     <Item type="Field" id="967FB753DC1D45A9AB6E0BB44BBA28B1" action="add">
      <border_width>0</border_width>
      <display_length_unit>px</display_length_unit>
      <field_type>dropdown</field_type>
      <font_color>#000000</font_color>
      <font_family>arial, helvetica, sans-serif</font_family>
      <font_size>8pt</font_size>
      <font_weight>bold</font_weight>
      <is_disabled>0</is_disabled>
      <is_visible>1</is_visible>
      <label xml:lang="en">Unit</label>
      <label_position>top</label_position>
      <list_no_blank>0</list_no_blank>
      <propertytype_id keyed_name="unit" type="Property">6EF283BEF0894DD1BE556E74F7A15AF0</propertytype_id>
      <sort_order>2304</sort_order>
      <source_id keyed_name="C1AA12DE4FAE4B24BC46663F40E2FBC3" type="Body">C1AA12DE4FAE4B24BC46663F40E2FBC3</source_id>
      <tab_index>40</tab_index>
      <tab_stop>1</tab_stop>
      <x>200</x>
      <y>90</y>
      <name>unit</name>
     </Item>
     <Item type="Field" id="E72138D8920D429F923736ABECEE65C0" action="add">
      <border_width>0</border_width>
      <display_length_unit>px</display_length_unit>
      <field_type>xclass</field_type>
      <font_color>#000000</font_color>
      <font_family>tahoma, arial, helvetica, sans-serif</font_family>
      <font_size>8pt</font_size>
      <font_weight>bold</font_weight>
      <is_disabled>0</is_disabled>
      <is_visible>1</is_visible>
      <label xml:lang="en">Extended Classification</label>
      <label_position>top</label_position>
      <list_no_blank>0</list_no_blank>
      <sort_order>5760</sort_order>
      <source_id keyed_name="C1AA12DE4FAE4B24BC46663F40E2FBC3" type="Body">C1AA12DE4FAE4B24BC46663F40E2FBC3</source_id>
      <tab_stop>1</tab_stop>
      <x>730</x>
      <y>10</y>
      <name>xclass</name>
     </Item>
    </Relationships>
   </Item>
   <Item type="Form Event" id="32439C1E398E493C92A14FABB4D77C27" action="add">
    <form_event>onformpopulated</form_event>
    <related_id keyed_name="Fill Form Fields" type="Method">
     <Item type="Method" action="get" select="id">
      <name>Fill Form Fields</name>
     </Item>
    </related_id>
    <sort_order>128</sort_order>
    <source_id keyed_name="CM2 Part Model" type="Form">558BC306774448158C25F43BF505B59F</source_id>
   </Item>
   <Item type="Form Event" id="E88D71AF00FA40A39B32B8CEF454E03C" action="add">
    <form_event>onformpopulated</form_event>
    <related_id keyed_name="PE_ShowCreateNewRevButton" type="Method">
     <Item type="Method" action="get" select="id">
      <name>PE_ShowCreateNewRevButton</name>
     </Item>
    </related_id>
    <sort_order>768</sort_order>
    <source_id keyed_name="CM2 Part Model" type="Form">558BC306774448158C25F43BF505B59F</source_id>
   </Item>
  </Relationships>
 </Item>
 <Item type="Field" id="41793AD558C44E82804A3992F2658224" action="edit">
  <!-- Please note: this AML depends on the "Part" ItemType. Please make sure it exists before running this. -->
  <propertytype_id>
   <Item type="Property" action="get" select="id">
    <name>classification</name>
    <source_id type="ItemType" keyed_name="Part">4F1AC04A2B484F3ABA4E20DB63808A88</source_id>
   </Item>
  </propertytype_id>
 </Item>
 <Item type="Field" id="384DE2802BAC4EE69DFC719053630FFB" action="edit">
  <!-- Please note: this AML depends on the "Part" ItemType. Please make sure it exists before running this. -->
  <propertytype_id>
   <Item type="Property" action="get" select="id">
    <name>effective_date</name>
    <source_id type="ItemType" keyed_name="Part">4F1AC04A2B484F3ABA4E20DB63808A88</source_id>
   </Item>
  </propertytype_id>
 </Item>
 <Item type="Field" id="DBD330939C8448369C27236E69F4816C" action="edit">
  <!-- Please note: this AML depends on the "Part" ItemType. Please make sure it exists before running this. -->
  <propertytype_id>
   <Item type="Property" action="get" select="id">
    <name>major_rev</name>
    <source_id type="ItemType" keyed_name="Part">4F1AC04A2B484F3ABA4E20DB63808A88</source_id>
   </Item>
  </propertytype_id>
 </Item>
 <Item type="Field" id="DAEDA95CED694F7BBC1A4AE0F63D5899" action="edit">
  <!-- Please note: this AML depends on the "Part" ItemType. Please make sure it exists before running this. -->
  <propertytype_id>
   <Item type="Property" action="get" select="id">
    <name>managed_by_id</name>
    <source_id type="ItemType" keyed_name="Part">4F1AC04A2B484F3ABA4E20DB63808A88</source_id>
   </Item>
  </propertytype_id>
 </Item>
 <Item type="Field" id="AAB0A203C4E242EB9F5153695216FCA5" action="edit">
  <!-- Please note: this AML depends on the "Part" ItemType. Please make sure it exists before running this. -->
  <propertytype_id>
   <Item type="Property" action="get" select="id">
    <name>owned_by_id</name>
    <source_id type="ItemType" keyed_name="Part">4F1AC04A2B484F3ABA4E20DB63808A88</source_id>
   </Item>
  </propertytype_id>
 </Item>
 <Item type="Field" id="650F419C4A194AACAD390AFCC546DDDC" action="edit">
  <!-- Please note: this AML depends on the "Part" ItemType. Please make sure it exists before running this. -->
  <propertytype_id>
   <Item type="Property" action="get" select="id">
    <name>release_date</name>
    <source_id type="ItemType" keyed_name="Part">4F1AC04A2B484F3ABA4E20DB63808A88</source_id>
   </Item>
  </propertytype_id>
 </Item>
 <Item type="Field" id="65C8ACA2C6EB4B47AEE156CD0CB35721" action="edit">
  <!-- Please note: this AML depends on the "Part" ItemType. Please make sure it exists before running this. -->
  <propertytype_id>
   <Item type="Property" action="get" select="id">
    <name>state</name>
    <source_id type="ItemType" keyed_name="Part">4F1AC04A2B484F3ABA4E20DB63808A88</source_id>
   </Item>
  </propertytype_id>
 </Item>
</AML>