<AML>
 <Item type="Form" id="E91F301F13CB4A15A0408A8FB40FCB20" action="add">
  <category_form>0</category_form>
  <height>439</height>
  <stylesheet><![CDATA[../styles/default.css]]></stylesheet>
  <width>784</width>
  <name>Part Alternate</name>
  <Relationships>
   <Item type="Body" id="833E88A21B0B42D79B0B064623E02050" action="add">
    <bg_color>#FFFFFF</bg_color>
    <sort_order>128</sort_order>
    <source_id keyed_name="Part Alternate" type="Form">E91F301F13CB4A15A0408A8FB40FCB20</source_id>
    <Relationships/>
   </Item>
  </Relationships>
 </Item>
</AML>